[
	{
		"__TYPE__": "SharedSliceContent",
		"variation": "default",
		"primary": {
			"heading": {
				"__TYPE__": "StructuredTextContent",
				"value": [
					{
						"type": "heading2",
						"content": {
							"text": "Range"
						}
					}
				]
			},
			"body": {
				"__TYPE__": "StructuredTextContent",
				"value": [
					{
						"type": "paragraph",
						"content": {
							"text": "Do laboris irure eiusmod eu consequat adipisicing officia commodo commodo excepteur cupidatat eu laborum et ullamco. Pariatur dolor magna exercitation. Eiusmod duis ullamco id ea elit."
						}
					}
				]
			},
			"icons": {
				"__TYPE__": "GroupContentType",
				"value": [
					{
						"__TYPE__": "GroupItemContent",
						"value": [
							[
								"icons",
								{
									"__TYPE__": "FieldContent",
									"value": "cloudflare",
									"type": "Select"
								}
							]
						]
					}
				]
			}
		},
		"items": []
	}
]